fast_bio-0.0.2.dist-info/RECORD
fast_bio-0.0.2.dist-info/top_level.txt
fast_bio-0.0.2.dist-info/WHEEL
fast_bio-0.0.2.dist-info/METADATA
fast_bio/__init__.cpython-39-x86_64-linux-gnu.so
